pymindcore/__init__.py
pymindcore/core.py
pymindcorecupy/__init__.py
pymindcorecupy/core.py
pymindcorecupy-0.1.0.dist-info/LICENSE
pymindcorecupy-0.1.0.dist-info/METADATA
pymindcorecupy-0.1.0.dist-info/WHEEL
pymindcorecupy-0.1.0.dist-info/top_level.txt
pymindcorecupy-0.1.0.dist-info/RECORD
