Metadata-Version: 2.1
Name: pymindcorecupy
Version: 0.1.0
Summary: A Python library for AI, easy to use, freely available for any use
Home-page: https://github.com/Dogz-R-Godz/Pymind-Cupy
Author: Dogz R Godz
Author-email: doggocam01@gmail.com
License: CC0 1.0 Universal (CC0 1.0) Public Domain Dedication
Classifier: Programming Language :: Python :: 3
Classifier: License :: CC0 1.0 Universal (CC0 1.0) Public Domain Dedication
License-File: LICENSE
Requires-Dist: numpy
Requires-Dist: Pillow
Requires-Dist: idx2numpy
Requires-Dist: cupy
